.gitignore
CHANGES.rst
CONTRIBUTORS.rst
README.rst
bootstrap.py
buildout.cfg
setup.py
docs/LICENSE.GPL
docs/LICENSE.txt
src/vs/__init__.py
src/vs.bootstrap.plonetheme.egg-info/PKG-INFO
src/vs.bootstrap.plonetheme.egg-info/SOURCES.txt
src/vs.bootstrap.plonetheme.egg-info/dependency_links.txt
src/vs.bootstrap.plonetheme.egg-info/entry_points.txt
src/vs.bootstrap.plonetheme.egg-info/namespace_packages.txt
src/vs.bootstrap.plonetheme.egg-info/not-zip-safe
src/vs.bootstrap.plonetheme.egg-info/requires.txt
src/vs.bootstrap.plonetheme.egg-info/top_level.txt
src/vs/bootstrap/__init__.py
src/vs/bootstrap/plonetheme/__init__.py
src/vs/bootstrap/plonetheme/configure.zcml
src/vs/bootstrap/plonetheme/testing.py
src/vs/bootstrap/plonetheme/testing.zcml
src/vs/bootstrap/plonetheme/profiles/default/metadata.xml
src/vs/bootstrap/plonetheme/profiles/default/theme.xml
src/vs/bootstrap/plonetheme/profiles/testing/metadata.xml
src/vs/bootstrap/plonetheme/static/edit.xml
src/vs/bootstrap/plonetheme/static/glossary.html
src/vs/bootstrap/plonetheme/static/glossary.xml
src/vs/bootstrap/plonetheme/static/manifest.cfg
src/vs/bootstrap/plonetheme/static/rules.xml
src/vs/bootstrap/plonetheme/static/theme.html
src/vs/bootstrap/plonetheme/static/css/bootstrap-responsive.css
src/vs/bootstrap/plonetheme/static/css/bootstrap-responsive.min.css
src/vs/bootstrap/plonetheme/static/css/bootstrap.css
src/vs/bootstrap/plonetheme/static/css/bootstrap.min.css
src/vs/bootstrap/plonetheme/static/font/FontAwesome.otf
src/vs/bootstrap/plonetheme/static/font/fontawesome-webfont.eot
src/vs/bootstrap/plonetheme/static/font/fontawesome-webfont.svg
src/vs/bootstrap/plonetheme/static/font/fontawesome-webfont.ttf
src/vs/bootstrap/plonetheme/static/font/fontawesome-webfont.woff
src/vs/bootstrap/plonetheme/static/img/glyphicons-halflings-white.png
src/vs/bootstrap/plonetheme/static/img/glyphicons-halflings.png
src/vs/bootstrap/plonetheme/static/js/bootstrap.js
src/vs/bootstrap/plonetheme/static/js/bootstrap.min.js
src/vs/bootstrap/plonetheme/static/js/jquery.js
src/vs/bootstrap/plonetheme/static/js/prettify.css
src/vs/bootstrap/plonetheme/static/js/prettify.js
src/vs/bootstrap/plonetheme/tests/__init__.py
src/vs/bootstrap/plonetheme/tests/test_setup.py