Metadata-Version: 1.1
Name: vs.bootstrap.plonetheme
Version: 1.0.6
Summary: Bootstrap theme for Plone
Home-page: https://github.com/veit/vs.bootstrap.plonetheme
Author: Veit Schiele
Author-email: kontakt@veit-schiele.de
License: gpl
Keywords: Zope Plone Bootstrap
Platform: UNKNOWN
Classifier: Environment :: Web Environment
Classifier: Framework :: Plone
Classifier: Operating System :: OS Independent
Classifier: Programming Language :: Python
Classifier: Programming Language :: Python :: 2.6
Classifier: Topic :: Software Development :: Libraries :: Python Modules
